{
  "projectInfo": {
    "projectName": "코오롱글로벌_코오롱베니트_안전관제비전AI",
    "startTime": "2025-06-24T08:22:41.310Z",
    "totalDepth": 2
  },
  "searchHistory": {
    "1차검색": {
      "depth": 2,
      "folderName": "Middle",
      "timestamp": "2025-06-24T08:22:41.310Z",
      "parentDimension": null,
      "totalQueries": 5,
      "queries": [
        {
          "index": 1,
          "query": "Kolon Global Benit safety monitoring vision AI features",
          "dimension": "Solution Overview",
          "researchGoal": "Understand the scope, functions, and unique value proposition of Kolon Global and Benit's safety monitoring vision AI solution, including key pain points it addresses.",
          "expectedResultFile": null
        },
        {
          "index": 2,
          "query": "Safety monitoring vision AI market size construction Korea",
          "dimension": "Market Landscape & Growth Dynamics",
          "researchGoal": "Analyze the market size, growth rate, and adoption trends of safety monitoring vision AI solutions in the Korean construction sector to identify business opportunities.",
          "expectedResultFile": null
        },
        {
          "index": 3,
          "query": "Construction site safety AI user segments Korea",
          "dimension": "Customer Segmentation & Demand Analysis",
          "researchGoal": "Identify key customer segments and personas in Korean construction sites for safety AI solutions, including their pain points and willingness to adopt such technologies.",
          "expectedResultFile": null
        },
        {
          "index": 4,
          "query": "Vision AI technologies for construction safety Korea",
          "dimension": "Technology Assessment & Business Value",
          "researchGoal": "Evaluate current and emerging vision AI technologies applicable to construction safety in Korea, assessing technical feasibility, integration complexity, and business value.",
          "expectedResultFile": null
        },
        {
          "index": 5,
          "query": "Regulations and risks for AI safety monitoring Korea",
          "dimension": "Risk & Regulatory Snapshot",
          "researchGoal": "Investigate regulatory requirements, compliance challenges, and potential risks related to deploying AI-based safety monitoring solutions in Korea's construction industry.",
          "expectedResultFile": null
        }
      ]
    },
    "2차검색": {
      "MarketLandscapeGrowthDynamics": {
        "depth": 1,
        "folderName": "FollowUp_1",
        "timestamp": "2025-06-24T08:24:58.070Z",
        "parentDimension": "Market Landscape & Growth Dynamics",
        "totalQueries": 3,
        "queries": [
          {
            "index": 1,
            "query": "South Korea safety monitoring vision AI market size",
            "dimension": null,
            "researchGoal": "Determine current market size and forecast for safety monitoring vision AI in South Korean construction sector.",
            "expectedResultFile": null
          },
          {
            "index": 2,
            "query": "Leading Korean AI vision companies construction safety",
            "dimension": null,
            "researchGoal": "Identify top South Korean companies and startups specializing in AI vision for construction safety monitoring and their technologies.",
            "expectedResultFile": null
          },
          {
            "index": 3,
            "query": "South Korea AI safety monitoring regulatory requirements",
            "dimension": null,
            "researchGoal": "Understand regulatory and data privacy laws impacting AI-based safety monitoring deployment in South Korean construction sites.",
            "expectedResultFile": null
          }
        ]
      },
      "SolutionOverview": {
        "depth": 1,
        "folderName": "FollowUp_1",
        "timestamp": "2025-06-24T08:24:59.924Z",
        "parentDimension": "Solution Overview",
        "totalQueries": 3,
        "queries": [
          {
            "index": 1,
            "query": "Kolon Benit safety AI solution scope",
            "dimension": null,
            "researchGoal": "Explore the definition and functional scope of Kolon Benit's safety monitoring vision AI solution.",
            "expectedResultFile": null
          },
          {
            "index": 2,
            "query": "Kolon Benit safety AI competitive landscape Korea",
            "dimension": null,
            "researchGoal": "Identify Korean-language findings and competitive snapshot of Kolon Benit's safety AI solutions.",
            "expectedResultFile": null
          },
          {
            "index": 3,
            "query": "Kolon Benit safety AI unmet needs value",
            "dimension": null,
            "researchGoal": "Investigate evidence of unmet safety monitoring needs and Kolon Benit's high-level value proposition.",
            "expectedResultFile": null
          }
        ]
      },
      "CustomerSegmentationDemandAnalysis": {
        "depth": 1,
        "folderName": "FollowUp_1",
        "timestamp": "2025-06-24T08:25:08.442Z",
        "parentDimension": "Customer Segmentation & Demand Analysis",
        "totalQueries": 3,
        "queries": [
          {
            "index": 1,
            "query": "Korean construction safety AI segment personas",
            "dimension": null,
            "researchGoal": "Identify detailed user segments and personas for construction safety AI in Korea including demographics and roles.",
            "expectedResultFile": null
          },
          {
            "index": 2,
            "query": "Korea AI construction safety market size forecast",
            "dimension": null,
            "researchGoal": "Determine current market size and growth projections for AI-based construction safety technologies in Korea.",
            "expectedResultFile": null
          },
          {
            "index": 3,
            "query": "Barriers to AI safety adoption Korean construction",
            "dimension": null,
            "researchGoal": "Explore perceptions and adoption barriers of AI safety solutions among Korean construction firms and user groups.",
            "expectedResultFile": null
          }
        ]
      },
      "TechnologyAssessmentBusinessValue": {
        "depth": 1,
        "folderName": "FollowUp_1",
        "timestamp": "2025-06-24T08:31:07.642Z",
        "parentDimension": "Technology Assessment & Business Value",
        "totalQueries": 3,
        "queries": [
          {
            "index": 1,
            "query": "Vision AI construction safety solution scope Korea",
            "dimension": null,
            "researchGoal": "Understand the definition and scope of Vision AI safety solutions in Korean construction",
            "expectedResultFile": null
          },
          {
            "index": 2,
            "query": "Vision AI construction safety market size Korea",
            "dimension": null,
            "researchGoal": "Assess the total addressable market and growth forecast for Vision AI in Korean construction safety",
            "expectedResultFile": null
          },
          {
            "index": 3,
            "query": "Vision AI construction safety ROI Korea",
            "dimension": null,
            "researchGoal": "Evaluate business value and return on investment of Vision AI technologies in Korean construction safety",
            "expectedResultFile": null
          }
        ]
      },
      "RiskRegulatorySnapshot": {
        "depth": 1,
        "folderName": "FollowUp_1",
        "timestamp": "2025-06-24T08:31:10.300Z",
        "parentDimension": "Risk & Regulatory Snapshot",
        "totalQueries": 3,
        "queries": [
          {
            "index": 1,
            "query": "South Korea AI safety monitoring solution scope",
            "dimension": null,
            "researchGoal": "Understand the definition and scope of AI safety monitoring solutions under South Korean regulations",
            "expectedResultFile": null
          },
          {
            "index": 2,
            "query": "South Korea AI regulatory market entry barriers",
            "dimension": null,
            "researchGoal": "Identify market entry barriers and competitive moats for AI safety monitoring in South Korea",
            "expectedResultFile": null
          },
          {
            "index": 3,
            "query": "South Korea AI compliance risks enforcement",
            "dimension": null,
            "researchGoal": "Explore regulatory, compliance, and enforcement risks for AI safety monitoring solutions in South Korea",
            "expectedResultFile": null
          }
        ]
      }
    }
  }
}